OpenPGPpy/__init__.py
OpenPGPpy/der_coding.py
OpenPGPpy/openpgp_card.py
OpenPGPpy-1.2.dist-info/LICENSE
OpenPGPpy-1.2.dist-info/METADATA
OpenPGPpy-1.2.dist-info/WHEEL
OpenPGPpy-1.2.dist-info/top_level.txt
OpenPGPpy-1.2.dist-info/RECORD
