Metadata-Version: 2.1
Name: OpenPGPpy
Version: 1.2
Summary: OpenPGP smartcard communication library
Home-page: https://github.com/bitlogik/OpenPGPpy
Author: BitLogiK
Author-email: contact@bitlogik.fr
License: GPLv3
Keywords: cryptography security openpgp hardware
Classifier: Programming Language :: Python :: 3 :: Only
Classifier: License :: OSI Approved :: GNU General Public License v3 (GPLv3)
Classifier: Intended Audience :: Developers
Classifier: Intended Audience :: Information Technology
Classifier: Intended Audience :: System Administrators
Classifier: Intended Audience :: Telecommunications Industry
Classifier: Topic :: Communications :: Email
Classifier: Topic :: Security :: Cryptography
Classifier: Topic :: Software Development :: Libraries :: Python Modules
Classifier: Topic :: System :: Hardware
Requires-Python: >=3.6
License-File: LICENSE
Requires-Dist: pyscard ==2.0.8
Provides-Extra: dev
Requires-Dist: PyNaCl ==1.5.0 ; extra == 'dev'
